ansys/aedt/toolkits/antenna/__init__.py
ansys/aedt/toolkits/antenna/run_toolkit.py
ansys/aedt/toolkits/antenna/backend/__init__.py
ansys/aedt/toolkits/antenna/backend/api.py
ansys/aedt/toolkits/antenna/backend/backend_properties.toml
ansys/aedt/toolkits/antenna/backend/models.py
ansys/aedt/toolkits/antenna/backend/run_backend.py
ansys/aedt/toolkits/antenna/backend/antenna_models/__init__.py
ansys/aedt/toolkits/antenna/backend/antenna_models/bowtie.py
ansys/aedt/toolkits/antenna/backend/antenna_models/common.py
ansys/aedt/toolkits/antenna/backend/antenna_models/conical_spiral.py
ansys/aedt/toolkits/antenna/backend/antenna_models/helix.py
ansys/aedt/toolkits/antenna/backend/antenna_models/horn.py
ansys/aedt/toolkits/antenna/backend/antenna_models/parameters.py
ansys/aedt/toolkits/antenna/backend/antenna_models/patch.py
ansys/aedt/toolkits/antenna/ui/__init__.py
ansys/aedt/toolkits/antenna/ui/actions.py
ansys/aedt/toolkits/antenna/ui/frontend_properties.toml
ansys/aedt/toolkits/antenna/ui/models.py
ansys/aedt/toolkits/antenna/ui/run_frontend.py
ansys/aedt/toolkits/antenna/ui/splash.png
ansys/aedt/toolkits/antenna/ui/splash.py
ansys/aedt/toolkits/antenna/ui/windows/antenna_catalog/__init__.py
ansys/aedt/toolkits/antenna/ui/windows/antenna_catalog/antenna_catalog.toml
ansys/aedt/toolkits/antenna/ui/windows/antenna_catalog/antenna_catalog_column.py
ansys/aedt/toolkits/antenna/ui/windows/antenna_catalog/antenna_catalog_column.ui
ansys/aedt/toolkits/antenna/ui/windows/antenna_catalog/antenna_catalog_menu.py
ansys/aedt/toolkits/antenna/ui/windows/antenna_catalog/antenna_catalog_page.py
ansys/aedt/toolkits/antenna/ui/windows/antenna_catalog/antenna_catalog_page.ui
ansys/aedt/toolkits/antenna/ui/windows/antenna_catalog/bowtie/__init__.py
ansys/aedt/toolkits/antenna/ui/windows/antenna_catalog/bowtie/bowtienormal/Bowtie.jpg
ansys/aedt/toolkits/antenna/ui/windows/antenna_catalog/bowtie/bowtienormal/parameters.toml
ansys_aedt_toolkits_antenna-0.8.0.dist-info/licenses/LICENSE
ansys_aedt_toolkits_antenna-0.8.0.dist-info/WHEEL
ansys_aedt_toolkits_antenna-0.8.0.dist-info/METADATA
ansys_aedt_toolkits_antenna-0.8.0.dist-info/RECORD
