Metadata-Version: 2.4
Name: ansys-aedt-toolkits-antenna
Version: 0.8.0
Summary: Toolkit to design antennas with Ansys AEDT.
Author-email: "ANSYS, Inc." <pyansys.core@ansys.com>
Maintainer-email: "ANSYS, Inc." <pyansys.core@ansys.com>
Requires-Python: >=3.10
License-Expression: MIT
Classifier: Development Status :: 4 - Beta
Classifier: Programming Language :: Python :: 3
Classifier: Operating System :: OS Independent
License-File: LICENSE
Requires-Dist: ansys-aedt-toolkits-common[all]
Requires-Dist: ansys-aedt-toolkits-common[all] ; extra == "all"
Requires-Dist: ansys-aedt-toolkits-common[doc] ; extra == "doc"
Requires-Dist: pyinstaller ; extra == "freeze"
Requires-Dist: ansys-aedt-toolkits-common[tests] ; extra == "tests"
Project-URL: Changelog, https://github.com/ansys/pyaedt-toolkits-antenna/blob/main/doc/source/changelog.rst
Project-URL: Discussions, https://github.com/ansys/pyaedt-toolkits-antenna/discussions
Project-URL: Documentation, https://aedt.antenna.toolkit.docs.pyansys.com
Project-URL: Issues, https://github.com/ansys/pyaedt-toolkits-antenna/issues
Project-URL: Releases, https://github.com/ansys/pyaedt-toolkits-antenna/releases
Project-URL: Source, https://github.com/ansys/pyaedt-toolkits-antenna
Provides-Extra: all
Provides-Extra: doc
Provides-Extra: freeze
Provides-Extra: tests
